LESim/README.md
LESim/__init__.py
LESim/version
LESim/RNN/RNN.py
LESim/RNN/__init__.py
LESim-0.0.1.dist-info/LICENSE
LESim-0.0.1.dist-info/METADATA
LESim-0.0.1.dist-info/WHEEL
LESim-0.0.1.dist-info/top_level.txt
LESim-0.0.1.dist-info/RECORD
