Metadata-Version: 2.1
Name: LESim
Version: 0.0.1
Summary: Learning-enabled Simulation
Home-page: https://github.com/rahulbhadani/LESim
Author: Rahul Bhadani
Author-email: rahulbhadani@email.arizona.edu
License: UNKNOWN
Keywords: python
Platform: UNKNOWN
Classifier: Programming Language :: Python :: 3
Classifier: Framework :: AsyncIO
Classifier: Topic :: Communications
Classifier: Topic :: Scientific/Engineering :: Visualization
Classifier: License :: OSI Approved :: MIT License
Requires-Dist: setuptools
Requires-Dist: setuptools-scm
Requires-Dist: importlib-resources
Requires-Dist: Sphinx (==3.2.1)
Requires-Dist: rinohtype
Requires-Dist: ipython
Requires-Dist: sphinx-rtd-theme
Requires-Dist: sphinx-autodoc-typehints
Requires-Dist: recommonmark
Requires-Dist: mkdocs
Requires-Dist: sphinx-bootstrap-theme
Requires-Dist: sphinx-markdown-parser
Requires-Dist: pymdown-extensions
Requires-Dist: m2r2
Requires-Dist: ytsphinx
Requires-Dist: python-dotenv
Requires-Dist: pycryptodomex
Requires-Dist: pyyaml
Requires-Dist: nbsphinx
Requires-Dist: pandoc
Requires-Dist: pandocfilters
Requires-Dist: yolk3k
